setup.cfg
setup.py
u2parser/__init__.py
u2parser/u2parser.py
u2parser.egg-info/PKG-INFO
u2parser.egg-info/SOURCES.txt
u2parser.egg-info/dependency_links.txt
u2parser.egg-info/requires.txt
u2parser.egg-info/top_level.txt